AUTHORS
CHANGELOG.rst
LICENSE
MANIFEST.in
README.rst
setup.py
django_url_tracker_fork.egg-info/PKG-INFO
django_url_tracker_fork.egg-info/SOURCES.txt
django_url_tracker_fork.egg-info/dependency_links.txt
django_url_tracker_fork.egg-info/requires.txt
django_url_tracker_fork.egg-info/top_level.txt
url_tracker/__init__.py
url_tracker/admin.py
url_tracker/apps.py
url_tracker/middleware.py
url_tracker/mixins.py
url_tracker/models.py
url_tracker/trackers.py
url_tracker/migrations/0001_initial.py
url_tracker/migrations/__init__.py