Metadata-Version: 1.1
Name: django-url-tracker-fork
Version: 0.2.0
Summary: A little app that trackes URL changes in a database table to provide HTTP 301 & 410 on request.
Home-page: https://github.com/saulshanabrook/django-url-tracker
Author: Sebastian Vetter
Author-email: sebastian.vetter@tangentone.com.au
License: BSD
Keywords: seo,django,framework
Platform: UNKNOWN
Classifier: Development Status :: 4 - Beta
Classifier: Environment :: Web Environment
Classifier: Framework :: Django
Classifier: Intended Audience :: Developers
Classifier: Programming Language :: Python
Classifier: License :: OSI Approved :: Apache Software License
Classifier: License :: OSI Approved :: BSD License
Classifier: Operating System :: OS Independent
Classifier: Programming Language :: Python :: 2
Classifier: Programming Language :: Python :: 2.6
Classifier: Programming Language :: Python :: 2.7
Classifier: Programming Language :: Python :: 3
Classifier: Programming Language :: Python :: 3.3
Classifier: Programming Language :: Python :: 3.4
Classifier: Programming Language :: Python :: 3.5
Classifier: Topic :: Software Development
